deskew/__init__.py
deskew/cli.py
deskew/py.typed
deskew-1.5.2.dist-info/LICENSE
deskew-1.5.2.dist-info/METADATA
deskew-1.5.2.dist-info/WHEEL
deskew-1.5.2.dist-info/entry_points.txt
deskew-1.5.2.dist-info/RECORD
